docmood/__init__.py
docmood/__main__.py
docmood/analyzer.py
docmood/config.py
docmood/config_loader.py
docmood/exit_code.py
docmood/imperative_indicators.py
docmood/mood.py
docmood/print_config.py
docmood/print_results.py
docmood/py.typed
docmood/scan.py
docmood/scanner.py
docmood/third_person_indicators.py
docmood-0.0.6.dist-info/licenses/LICENSE
docmood-0.0.6.dist-info/METADATA
docmood-0.0.6.dist-info/WHEEL
docmood-0.0.6.dist-info/entry_points.txt
docmood-0.0.6.dist-info/top_level.txt
docmood-0.0.6.dist-info/RECORD
