Metadata-Version: 2.4
Name: docmood
Version: 0.0.6
Summary: A Python tool that checks the grammatical mood consistency of function and method docstrings.
Author-email: Oleh <oleh.stefanovych@gmail.com>
License: MIT License
Project-URL: Homepage, https://github.com/Oleh-Stefanovych/docmood
Project-URL: Repository, https://github.com/Oleh-Stefanovych/docmood
Project-URL: Issues, https://github.com/Oleh-Stefanovych/docmood/issues
Keywords: cli,docstring,grammatical mood,linter,python,tool,imperative,declarative,third-person
Classifier: Development Status :: 3 - Alpha
Classifier: Environment :: Console
Classifier: Intended Audience :: Developers
Classifier: License :: OSI Approved :: MIT License
Classifier: Programming Language :: Python :: 3
Classifier: Programming Language :: Python :: 3 :: Only
Classifier: Programming Language :: Python :: 3.8
Classifier: Programming Language :: Python :: 3.9
Classifier: Programming Language :: Python :: 3.10
Classifier: Programming Language :: Python :: 3.11
Classifier: Programming Language :: Python :: 3.12
Classifier: Programming Language :: Python :: 3.13
Classifier: Typing :: Typed
Requires-Python: >=3.8
License-File: LICENSE
Requires-Dist: tomli>=2.0.0; python_version < "3.11"
Dynamic: license-file
